aermanager/aerparser.py
aermanager/annotate_aedat.py
aermanager/cvat_dataset_generator.py
aermanager/dataset_generator.py
aermanager/datasets.py
aermanager/liveaer.py
aermanager/parsers.py
aermanager/preprocess.py
aermanager/transform.py
aermanager/visualization.py
aermanager/cvat/aedat_to_video.py
aermanager/cvat/load_annotations.py
aermanager/cvat/parser.py
aermanager-0.3.0.dist-info/AUTHORS
aermanager-0.3.0.dist-info/LICENSE
aermanager-0.3.0.dist-info/METADATA
aermanager-0.3.0.dist-info/WHEEL
aermanager-0.3.0.dist-info/pbr.json
aermanager-0.3.0.dist-info/top_level.txt
aermanager-0.3.0.dist-info/RECORD
