Metadata-Version: 2.1
Name: aermanager
Version: 0.3.0
Summary: Python package for managing AER data, including .aedat4 files, live DV streams, and interfacing with pyTorch.
Home-page: UNKNOWN
Author: SynSense (formerly AiCTX)
Author-email: sinabs@synsense.ai
License: GNU AGPLv3
Project-URL: Source Code, https://gitlab.com/synsense/aermanager
Project-URL: Documentation, https://synsense.gitlab.io/aermanager
Keywords: spiking,SNN,AER,DVS
Platform: UNKNOWN
Classifier: Development Status :: 4 - Beta
Classifier: Environment :: Console
Classifier: Intended Audience :: Science/Research
Classifier: Intended Audience :: Developers
Classifier: License :: OSI Approved :: GNU Affero General Public License v3 or later (AGPLv3+)
Classifier: Programming Language :: Python :: 3
Requires-Dist: dv
Requires-Dist: tqdm
Requires-Dist: numpy
Requires-Dist: h5py (>=3)
Requires-Dist: lxml
Requires-Dist: scikit-image
Requires-Dist: torchvision
Requires-Dist: pandas
